_oitnb_lib2to3/Grammar.txt
_oitnb_lib2to3/PatternGrammar.txt
_oitnb_lib2to3/__init__.py
_oitnb_lib2to3/pygram.py
_oitnb_lib2to3/pytree.py
_oitnb_lib2to3/pgen2/__init__.py
_oitnb_lib2to3/pgen2/conv.py
_oitnb_lib2to3/pgen2/driver.py
_oitnb_lib2to3/pgen2/grammar.py
_oitnb_lib2to3/pgen2/literals.py
_oitnb_lib2to3/pgen2/parse.py
_oitnb_lib2to3/pgen2/pgen.py
_oitnb_lib2to3/pgen2/token.py
_oitnb_lib2to3/pgen2/tokenize.py
oitnb/__init__.py
oitnb/oitnb.py
oitnb/omeld.py
oitnb/parseconfig.py
oitnb-0.2.2.dist-info/LICENSE
oitnb-0.2.2.dist-info/METADATA
oitnb-0.2.2.dist-info/WHEEL
oitnb-0.2.2.dist-info/entry_points.txt
oitnb-0.2.2.dist-info/namespace_packages.txt
oitnb-0.2.2.dist-info/top_level.txt
oitnb-0.2.2.dist-info/RECORD
