Metadata-Version: 2.1
Name: oitnb
Version: 0.2.2
Summary: oitnb works around some of black's issues
Home-page: https://sourceforge.net/p/oitnb/code/ci/default/tree
Author: Anthon van der Neut
Author-email: a.van.der.neut@ruamel.eu
License: MIT
Keywords: automation formatter black pep8
Platform: UNKNOWN
Classifier: Development Status :: 4 - Beta
Classifier: Environment :: Console
Classifier: Intended Audience :: Developers
Classifier: License :: OSI Approved :: MIT License
Classifier: Operating System :: OS Independent
Classifier: Programming Language :: Python
Classifier: Programming Language :: Python :: 3 :: Only
Classifier: Programming Language :: Python :: 3.6
Classifier: Programming Language :: Python :: 3.7
Classifier: Topic :: Software Development :: Libraries :: Python Modules
Classifier: Topic :: Software Development :: Quality Assurance
Requires-Python: >=3.6
Requires-Dist: click (>=6.5)
Requires-Dist: attrs (>=18.1.0)
Requires-Dist: appdirs
Requires-Dist: regex (>=2020.1.8)
Requires-Dist: typed-ast (>=1.4.0)
Requires-Dist: pathspec (<1,>=0.6)
Requires-Dist: typing-extensions (>=3.7.4)
Requires-Dist: mypy-extensions (>=0.4.3)
